setup.py
UCloud/__init__.py
ucloud_py.egg-info/PKG-INFO
ucloud_py.egg-info/SOURCES.txt
ucloud_py.egg-info/dependency_links.txt
ucloud_py.egg-info/top_level.txt