Metadata-Version: 1.0
Name: ucloud-py
Version: 0.2
Summary: UCloud(UCloud.cn) Python SDK
Home-page: https://github.com/jeffkit/UCloud
Author: jeff kit
Author-email: bbmyth@gmail.com
License: UNKNOWN
Platform: UNKNOWN
